[{"id":"pet-spa-grooming-by-heads-up-for-tails-chandivali-mumbai-05271400","name":"Pet Spa & Grooming by Heads Up For Tails - Chandivali, Mumbai","category":"Pet Grooming & Spa","category_icon":"🛁","category_slug":"pet-grooming-spa","city":"Chandivali","city_slug":"chandivali","state":"","country":"IN","address":"ABC CHS LTD, Lake Primrose, Shop LG 07, C Wing, Lake Homes Private Rd, Chandivali, Maharashtra 400072","phone":"082910 69337","website":"https://headsupfortails.com/pages/pet-spa","pincode":"400072","rating":4.4,"review_count":78,"google_cid":"11519552169805271400","gmb_link":"https://www.google.com/maps?cid=11519552169805271400","active":"yes"}]