[{"id":"all-barks-of-life-hotel-dog-daycare-dog-hotel-94226444","name":"All Barks Of Life Hotel - Dog Daycare & Dog Hotel","category":"Pet Boarding & Daycare","category_icon":"🏠","category_slug":"pet-boarding-daycare","city":"Burien","city_slug":"burien","state":"Washington","country":"US","address":"1043 S 140th St, Burien, WA 98168, United States","phone":"+1 206-333-4535","website":"https://dogboardingseattle.com/","pincode":"98168","rating":4.9,"review_count":317,"google_cid":"8774362809894226444","gmb_link":"https://www.google.com/maps?cid=8774362809894226444","active":"yes"},{"id":"wild-birds-unlimited-72466174","name":"Wild Birds Unlimited","category":"Specialty Vets (exotics, avian, reptiles)","category_icon":"🦜","category_slug":"specialty-vets-exotics-avian-reptiles","city":"Burien","city_slug":"burien","state":"Washington","country":"US","address":"15858 1st Ave S, Burien, WA 98148, United States","phone":"+1 206-241-3201","website":"https://southseattle.wbu.com/?utm_source=google&utm_medium=local&utm_campaign=localmaps&utm_content=373","pincode":"98148","rating":4.6,"review_count":194,"google_cid":"8045655907272466174","gmb_link":"https://www.google.com/maps?cid=8045655907272466174","active":"yes"},{"id":"the-painted-pooch-31817872","name":"The Painted Pooch","category":"Pet Grooming & Spa","category_icon":"🛁","category_slug":"pet-grooming-spa","city":"Burien","city_slug":"burien","state":"Washington","country":"US","address":"641 SW 153rd St, Burien, WA 98166, United States","phone":"+1 206-246-7700","website":"https://www.facebook.com/ThePaintedPooch98166/","pincode":"98166","rating":4.6,"review_count":50,"google_cid":"17426998148431817872","gmb_link":"https://www.google.com/maps?cid=17426998148431817872","active":"yes"}]