[{"id":"urgentvet-57493135","name":"UrgentVet","category":"Emergency Animal Hospital","category_icon":"🚑","category_slug":"emergency-animal-hospital","city":"Coon Rapids","city_slug":"coon-rapids","state":"Minnesota","country":"US","address":"12475 Riverdale Blvd Suite L, Coon Rapids, MN 55433, United States","phone":"+1 612-431-7500","website":"https://urgentvet.com/location/coon-rapids-mn/","pincode":"55433","rating":4.7,"review_count":454,"google_cid":"9753606493357493135","gmb_link":"https://www.google.com/maps?cid=9753606493357493135","active":"yes"}]