[{"id":"secret-garden-pet-resort-41702899","name":"Secret Garden Pet Resort","category":"Pet Boarding & Daycare","category_icon":"🏠","category_slug":"pet-boarding-daycare","city":"East Bridgewater","city_slug":"east-bridgewater","state":"Massachusetts","country":"US","address":"1040 Central St, East Bridgewater, MA 02333, United States","phone":"+1 508-378-1400","website":"http://www.secretgardenpetresort.com/","pincode":"02333","rating":4.8,"review_count":194,"google_cid":"2106863508941702899","gmb_link":"https://www.google.com/maps?cid=2106863508941702899","active":"yes"},{"id":"mobile-animal-care-01608527","name":"Mobile Animal Care","category":"Mobile Vet Services","category_icon":"🚐","category_slug":"mobile-vet-services","city":"East Bridgewater","city_slug":"east-bridgewater","state":"Massachusetts","country":"US","address":"265 Union St, East Bridgewater, MA 02333, United States","phone":"+1 508-378-0082","website":"https://www.facebook.com/MobileAnimalCare/","pincode":"02333","rating":4.8,"review_count":71,"google_cid":"3283565927001608527","gmb_link":"https://www.google.com/maps?cid=3283565927001608527","active":"yes"}]