[{"id":"passport-health-grover-beach-travel-clinic-96306560","name":"Passport Health Grover Beach Travel Clinic","category":"Vaccination Centers","category_icon":"💉","category_slug":"vaccination-centers","city":"Grover Beach","city_slug":"grover-beach","state":"California","country":"US","address":"910 Ramona Ave suite h, Grover Beach, CA 93433, United States","phone":"+1 805-909-4232","website":"http://www.passporthealthusa.com/locations/ca/grover-beach/381//?utm_source=gmb&utm_medium=organic&utm_campaign=GMB_Insights&utm_content=grover-beach","pincode":"93433","rating":5.0,"review_count":475,"google_cid":"5820332250696306560","gmb_link":"https://www.google.com/maps?cid=5820332250696306560","active":"yes"}]