[{"id":"backyard-bird-shop-56570081","name":"Backyard Bird Shop","category":"Specialty Vets (exotics, avian, reptiles)","category_icon":"🦜","category_slug":"specialty-vets-exotics-avian-reptiles","city":"Happy Valley","city_slug":"happy-valley","state":"Oregon","country":"US","address":"13200 SE 172nd Ave Suite 154, Happy Valley, OR 97086, United States","phone":"+1 503-445-2699","website":"http://www.backyardbirdshop.com/","pincode":"97086","rating":4.8,"review_count":403,"google_cid":"587411735456570081","gmb_link":"https://www.google.com/maps?cid=587411735456570081","active":"yes"},{"id":"natures-acres-boarding-kennels-74941258","name":"Natures Acres Boarding Kennels","category":"Pet Boarding & Daycare","category_icon":"🏠","category_slug":"pet-boarding-daycare","city":"Happy Valley","city_slug":"happy-valley","state":"Oregon","country":"US","address":"18651 SE Foster Rd, Damascus, OR 97089, United States","phone":"+1 503-666-4800","website":"http://naturesacreskennel.com/","pincode":"97089","rating":4.5,"review_count":310,"google_cid":"14318792498874941258","gmb_link":"https://www.google.com/maps?cid=14318792498874941258","active":"yes"}]