[{"id":"animal-medical-center-of-highland-village-4702E+18","name":"Animal Medical Center of Highland Village","category":"Veterinary Clinics","category_icon":"🩺","category_slug":"veterinary-clinics","city":"Highland Village","city_slug":"highland-village","state":"Texas","country":"US","address":"2810 Justin Rd, Highland Village, TX 75077, United States","phone":"+1 972-317-7387","website":"https://animalmedicalcenterhv.com/?utm_source=gmb&utm_medium=organic","pincode":"75077","rating":4.9,"review_count":257,"google_cid":"1.24702E+18","gmb_link":"https://www.google.com/maps?cid=1.24702E+18","active":"yes"},{"id":"highland-village-animal-medical-center-of-highland-village-66757503","name":"Animal Medical Center of Highland Village","category":"Veterinary Clinics","category_icon":"🩺","category_slug":"veterinary-clinics","city":"Highland Village","city_slug":"highland-village","state":"Texas","country":"US","address":"2810 Justin Rd, Highland Village, TX 75077, United States","phone":"+1 972-317-7387","website":"https://animalmedicalcenterhv.com/?utm_source=gmb&utm_medium=organic","pincode":"75077","rating":4.9,"review_count":143,"google_cid":"1247018042566757503","gmb_link":"https://www.google.com/maps?cid=1247018042566757503","active":"yes"},{"id":"animal-medical-center-of-highland-village-66757503","name":"Animal Medical Center of Highland Village","category":"Emergency Animal Hospital","category_icon":"🚑","category_slug":"emergency-animal-hospital","city":"Highland Village","city_slug":"highland-village","state":"Texas","country":"US","address":"2810 Justin Rd, Highland Village, TX 75077, United States","phone":"+1 972-317-7387","website":"https://animalmedicalcenterhv.com/?utm_source=gmb&utm_medium=organic","pincode":"75077","rating":4.8,"review_count":143,"google_cid":"1247018042566757503","gmb_link":"https://www.google.com/maps?cid=1247018042566757503","active":"yes"},{"id":"dogtopia-of-highland-village-9981E+18","name":"Dogtopia of Highland Village","category":"Pet Boarding & Daycare","category_icon":"🏠","category_slug":"pet-boarding-daycare","city":"Highland Village","city_slug":"highland-village","state":"Texas","country":"US","address":"1830 Justin Rd, Highland Village, TX 75077, United States","phone":"+1 972-264-1178","website":"https://www.dogtopia.com/highland-village/","pincode":"75077","rating":4.7,"review_count":106,"google_cid":"6.29981E+18","gmb_link":"https://www.google.com/maps?cid=6.29981E+18","active":"yes"},{"id":"dogtopia-of-highland-village-93524734","name":"Dogtopia of Highland Village","category":"Pet Boarding & Daycare","category_icon":"🏠","category_slug":"pet-boarding-daycare","city":"Highland Village","city_slug":"highland-village","state":"Texas","country":"US","address":"1830 Justin Rd, Highland Village, TX 75077, United States","phone":"+1 972-264-1178","website":"https://www.dogtopia.com/highland-village/","pincode":"75077","rating":4.7,"review_count":50,"google_cid":"6299809943493524734","gmb_link":"https://www.google.com/maps?cid=6299809943493524734","active":"yes"},{"id":"highland-village-dogtopia-of-highland-village-93524734","name":"Dogtopia of Highland Village","category":"Pet Boarding & Daycare","category_icon":"🏠","category_slug":"pet-boarding-daycare","city":"Highland Village","city_slug":"highland-village","state":"Texas","country":"US","address":"1830 Justin Rd, Highland Village, TX 75077, United States","phone":"+1 972-264-1178","website":"https://www.dogtopia.com/highland-village/","pincode":"75077","rating":4.7,"review_count":50,"google_cid":"6299809943493524734","gmb_link":"https://www.google.com/maps?cid=6299809943493524734","active":"yes"}]