[{"id":"pet-solutions-texas-96740166","name":"Pet Solutions Texas","category":"Pet Sitting (In-home Care)","category_icon":"🛏️","category_slug":"pet-sitting-in-home-care","city":"Hollywood Park","city_slug":"hollywood-park","state":"Texas","country":"US","address":"101 El Cerrito Cir, San Antonio, TX 78232, United States","phone":"+1 210-854-4145","website":"","pincode":"78232","rating":5.0,"review_count":194,"google_cid":"18199143606196740166","gmb_link":"https://www.google.com/maps?cid=18199143606196740166","active":"yes"},{"id":"alamo-feline-health-center-19496039","name":"Alamo Feline Health Center","category":"Pet Therapy Services","category_icon":"💖","category_slug":"pet-therapy-services","city":"Hollywood Park","city_slug":"hollywood-park","state":"Texas","country":"US","address":"16201 San Pedro Ave, Hollywood Park, TX 78232, United States","phone":"+1 210-404-2287","website":"http://alamofeline.com/","pincode":"78232","rating":4.7,"review_count":389,"google_cid":"5088681336219496039","gmb_link":"https://www.google.com/maps?cid=5088681336219496039","active":"yes"}]