[{"id":"reid-clinic-74421221","name":"Reid Clinic","category":"Vaccination Centers","category_icon":"💉","category_slug":"vaccination-centers","city":"Lackland Air Force Base","city_slug":"lackland-air-force-base","state":"Texas","country":"US","address":"1940 Carswell Ave Bldg. 7002, Lackland Air Force Base, TX 78236, United States","phone":"+1 210-916-9900","website":"https://wilfordhall.tricare.mil/Clinics/Reid-Clinic","pincode":"78236","rating":3.3,"review_count":208,"google_cid":"4671218376674421221","gmb_link":"https://www.google.com/maps?cid=4671218376674421221","active":"yes"},{"id":"wilford-hall-ambulatory-surgical-center-40897763","name":"Wilford Hall Ambulatory Surgical Center","category":"Vaccination Centers","category_icon":"💉","category_slug":"vaccination-centers","city":"Lackland Air Force Base","city_slug":"lackland-air-force-base","state":"Texas","country":"US","address":"1100 Wilford Hall Loop, Lackland Air Force Base, TX 78236, United States","phone":"+1 210-292-4277","website":"","pincode":"78236","rating":3.0,"review_count":382,"google_cid":"13517915495440897763","gmb_link":"https://www.google.com/maps?cid=13517915495440897763","active":"yes"}]