[{"id":"cityvet-lone-tree-06026479","name":"CityVet | Lone Tree","category":"Veterinary Clinics","category_icon":"🩺","category_slug":"veterinary-clinics","city":"Lone Tree","city_slug":"lone-tree","state":"Colorado","country":"US","address":"8330 Willow St #200, Lone Tree, CO 80124, United States","phone":"+1 303-493-0100","website":"https://www.cityvet.com/lone-tree/?utm_source=yext&utm_medium=organic&utm_campaign=lone-tree","pincode":"80124","rating":5.0,"review_count":475,"google_cid":"16601034636106026479","gmb_link":"https://www.google.com/maps?cid=16601034636106026479","active":"yes"},{"id":"k9-resorts-luxury-pet-hotel-lone-tree-83566301","name":"K9 Resorts Luxury Pet Hotel Lone Tree","category":"Pet Boarding & Daycare","category_icon":"🏠","category_slug":"pet-boarding-daycare","city":"Lone Tree","city_slug":"lone-tree","state":"Colorado","country":"US","address":"7475 Park Meadows Dr, Lone Tree, CO 80124, United States","phone":"+1 303-529-7791","website":"https://www.k9resorts.com/lone-tree/","pincode":"80124","rating":4.9,"review_count":317,"google_cid":"12961479747883566301","gmb_link":"https://www.google.com/maps?cid=12961479747883566301","active":"yes"}]