[{"id":"menifee-pet-sitting-dog-cat-parrot-care-sitter-08295340","name":"Menifee Pet Sitting - Dog Cat Parrot Care Sitter","category":"Pet Sitting (In-home Care)","category_icon":"🛏️","category_slug":"pet-sitting-in-home-care","city":"Menifee","city_slug":"menifee","state":"California","country":"US","address":"Stillwater Dr, Menifee, CA 92584, United States","phone":"+1 951-639-3300","website":"http://www.menifeepetsitting.com/","pincode":"92584","rating":4.9,"review_count":194,"google_cid":"17039085557708295340","gmb_link":"https://www.google.com/maps?cid=17039085557708295340","active":"yes"},{"id":"menifee-birds-n-paradise-81281122","name":"Birds-N-Paradise","category":"Specialty Vets (exotics, avian, reptiles)","category_icon":"🦜","category_slug":"specialty-vets-exotics-avian-reptiles","city":"Menifee","city_slug":"menifee","state":"California","country":"US","address":"27620 Encanto Dr, Menifee, CA 92586, United States","phone":"+1 951-309-1580","website":"","pincode":"92586","rating":4.5,"review_count":85,"google_cid":"14115157355281281122","gmb_link":"https://www.google.com/maps?cid=14115157355281281122","active":"yes"},{"id":"briarcliff-pet-resort-36829982","name":"Briarcliff Pet Resort","category":"Pet Boarding & Daycare","category_icon":"🏠","category_slug":"pet-boarding-daycare","city":"Menifee","city_slug":"menifee","state":"California","country":"US","address":"31585 Briggs Rd, Menifee, CA 92584, United States","phone":"+1 951-246-7200","website":"http://www.briarcliffpetresort.com/","pincode":"92584","rating":4.4,"review_count":194,"google_cid":"13907907111236829982","gmb_link":"https://www.google.com/maps?cid=13907907111236829982","active":"yes"}]