[{"id":"oakland-oakvet-animal-specialty-hospital-19636521","name":"OakVet Animal Specialty Hospital","category":"Emergency Animal Hospital","category_icon":"🚑","category_slug":"emergency-animal-hospital","city":"Oakland","city_slug":"oakland","state":"California","country":"US","address":"1133 7th St, Oakland, CA 94607, United States","phone":"+1 510-279-6821","website":"https://www.oakvetash.com/","pincode":"94607","rating":4.6,"review_count":187,"google_cid":"5675835284919636521","gmb_link":"https://www.google.com/maps?cid=5675835284919636521","active":"yes"},{"id":"oakvet-animal-specialty-hospital-19636521","name":"OakVet Animal Specialty Hospital","category":"Specialty Vets (exotics, avian, reptiles)","category_icon":"🦜","category_slug":"specialty-vets-exotics-avian-reptiles","city":"Oakland","city_slug":"oakland","state":"California","country":"US","address":"1133 7th St, Oakland, CA 94607, United States","phone":"+1 510-279-6821","website":"https://www.oakvetash.com/","pincode":"94607","rating":4.6,"review_count":187,"google_cid":"5675835284919636521","gmb_link":"https://www.google.com/maps?cid=5675835284919636521","active":"yes"},{"id":"hopalong-foster-program-at-marin-humane-88094913","name":"Hopalong Foster Program at Marin Humane","category":"Specialty Vets (exotics, avian, reptiles)","category_icon":"🦜","category_slug":"specialty-vets-exotics-avian-reptiles","city":"Oakland","city_slug":"oakland","state":"California","country":"US","address":"1035 22nd Ave #3, Oakland, CA 94606, United States","phone":"+1 510-267-1915","website":"http://www.marinhumane.org/hopalong","pincode":"94606","rating":4.4,"review_count":129,"google_cid":"11549214483388094913","gmb_link":"https://www.google.com/maps?cid=11549214483388094913","active":"yes"},{"id":"veterinary-emergency-clinic-of-central-florida-oakland-fl-55047398","name":"Veterinary Emergency Clinic of Central Florida | Oakland, FL","category":"Emergency Animal Hospital","category_icon":"🚑","category_slug":"emergency-animal-hospital","city":"Oakland","city_slug":"oakland","state":"Florida","country":"US","address":"16369 W Colonial Dr, Oakland, FL 34787, United States","phone":"+1 407-644-4449 ext. 5","website":"http://www.veconline.com/","pincode":"34787","rating":4.0,"review_count":338,"google_cid":"2044161845055047398","gmb_link":"https://www.google.com/maps?cid=2044161845055047398","active":"yes"},{"id":"oakland-veterinary-emergency-clinic-of-central-florida-oakland-fl-55047398","name":"Veterinary Emergency Clinic of Central Florida | Oakland, FL","category":"Emergency Animal Hospital","category_icon":"🚑","category_slug":"emergency-animal-hospital","city":"Oakland","city_slug":"oakland","state":"Florida","country":"US","address":"16369 W Colonial Dr, Oakland, FL 34787, United States","phone":"+1 407-644-4449 ext. 5","website":"http://www.veconline.com/","pincode":"34787","rating":4.0,"review_count":338,"google_cid":"2044161845055047398","gmb_link":"https://www.google.com/maps?cid=2044161845055047398","active":"yes"},{"id":"therapypets-75404839","name":"TherapyPets","category":"Pet Therapy Services","category_icon":"💖","category_slug":"pet-therapy-services","city":"Oakland","city_slug":"oakland","state":"California","country":"US","address":"201 13th St STE 32288, Oakland, CA 94604, United States","phone":"+1 510-287-9042","website":"http://www.therapypets.org/","pincode":"94604","rating":1.0,"review_count":187,"google_cid":"6169308919375404839","gmb_link":"https://www.google.com/maps?cid=6169308919375404839","active":"yes"},{"id":"oakland-therapypets-75404839","name":"TherapyPets","category":"Pet Therapy Services","category_icon":"💖","category_slug":"pet-therapy-services","city":"Oakland","city_slug":"oakland","state":"California","country":"US","address":"201 13th St STE 32288, Oakland, CA 94604, United States","phone":"+1 510-287-9042","website":"http://www.therapypets.org/","pincode":"94604","rating":1.0,"review_count":187,"google_cid":"6169308919375404839","gmb_link":"https://www.google.com/maps?cid=6169308919375404839","active":"yes"}]