[{"id":"gulf-coast-veterinary-center-of-tampa-57181738","name":"Gulf Coast Veterinary Center of Tampa","category":"Specialty Vets (exotics, avian, reptiles)","category_icon":"🦜","category_slug":"specialty-vets-exotics-avian-reptiles","city":"the Citrus Park","city_slug":"the-citrus-park","state":"Florida","country":"US","address":"6902 W Linebaugh Ave, Tampa, FL 33625, United States","phone":"+1 813-746-3979","website":"https://gulfcoasttampa.com/?utm_source=GMB-%20Website&utm_medium=GMB&utm_campaign=GMB","pincode":"33625","rating":4.8,"review_count":201,"google_cid":"791180330957181738","gmb_link":"https://www.google.com/maps?cid=791180330957181738","active":"yes"},{"id":"ehrlich-animal-hospital-arthritis-therapy-center-41535030","name":"Ehrlich Animal Hospital & Arthritis Therapy Center","category":"Pet Physiotherapy & Rehab","category_icon":"🩹","category_slug":"pet-physiotherapy-rehab","city":"the Citrus Park","city_slug":"the-citrus-park","state":"Florida","country":"US","address":"8009 Gunn Hwy, Tampa, FL 33626, United States","phone":"+1 813-920-0566","website":"http://www.ehrlichanimalhospital.com/services/e-pet-health/","pincode":"33626","rating":4.7,"review_count":461,"google_cid":"15777484719441535030","gmb_link":"https://www.google.com/maps?cid=15777484719441535030","active":"yes"},{"id":"lakeside-animal-hospital-58330157","name":"Lakeside Animal Hospital","category":"Veterinary Clinics","category_icon":"🩺","category_slug":"veterinary-clinics","city":"the Citrus Park","city_slug":"the-citrus-park","state":"Florida","country":"US","address":"8521 Gunn Hwy, Odessa, FL 33556, United States","phone":"+1 813-920-5100","website":"https://www.lakesideah.com/","pincode":"33556","rating":4.7,"review_count":410,"google_cid":"13398031244058330157","gmb_link":"https://www.google.com/maps?cid=13398031244058330157","active":"yes"},{"id":"adventhealth-centra-care-citrus-park-60022878","name":"AdventHealth Centra Care Citrus Park","category":"Vaccination Centers","category_icon":"💉","category_slug":"vaccination-centers","city":"the Citrus Park","city_slug":"the-citrus-park","state":"Florida","country":"US","address":"6930 Gunn Hwy, Tampa, FL 33625, United States","phone":"+1 813-543-0800","website":"https://centracare.adventhealth.com/urgent-care/citrus-park","pincode":"33625","rating":4.6,"review_count":352,"google_cid":"1004098006160022878","gmb_link":"https://www.google.com/maps?cid=1004098006160022878","active":"yes"},{"id":"citrus-park-animal-bird-exotics-hospital-13069832","name":"Citrus Park Animal, Bird & Exotics Hospital","category":"Specialty Vets (exotics, avian, reptiles)","category_icon":"🦜","category_slug":"specialty-vets-exotics-avian-reptiles","city":"the Citrus Park","city_slug":"the-citrus-park","state":"Florida","country":"US","address":"7607 Ehrlich Rd, Tampa, FL 33625, United States","phone":"+1 813-920-6656","website":"http://www.citrusparkanimalhospital.com/","pincode":"33625","rating":4.6,"review_count":150,"google_cid":"916351035113069832","gmb_link":"https://www.google.com/maps?cid=916351035113069832","active":"yes"},{"id":"tgh-urgent-care-powered-by-fast-track-westchase-71357904","name":"TGH Urgent Care powered by Fast Track (Westchase)","category":"Vaccination Centers","category_icon":"💉","category_slug":"vaccination-centers","city":"the Citrus Park","city_slug":"the-citrus-park","state":"Florida","country":"US","address":"11969 Sheldon Rd, Tampa, FL 33626, United States","phone":"+1 813-925-1903","website":"https://www.fasttrackurgentcare.com/locations-and-hours/westchase/","pincode":"33626","rating":4.2,"review_count":468,"google_cid":"13908636011471357904","gmb_link":"https://www.google.com/maps?cid=13908636011471357904","active":"yes"}]