[{"id":"wilton-manors-animal-hospital-and-premier-pet-care-86985082","name":"Wilton Manors Animal Hospital and Premier Pet Care","category":"Veterinary Clinics","category_icon":"🩺","category_slug":"veterinary-clinics","city":"Wilton Manors","city_slug":"wilton-manors","state":"Florida","country":"US","address":"2201 N Dixie Hwy, Wilton Manors, FL 33305, United States","phone":"+1 954-541-2550","website":"https://wiltonmanorsanimalhospital.net/","pincode":"33305","rating":4.6,"review_count":122,"google_cid":"13385660730686985082","gmb_link":"https://www.google.com/maps?cid=13385660730686985082","active":"yes"},{"id":"dog-hotels-fort-lauderdale-04302420","name":"DOG Hotels Fort Lauderdale","category":"Pet Boarding & Daycare","category_icon":"🏠","category_slug":"pet-boarding-daycare","city":"Wilton Manors","city_slug":"wilton-manors","state":"Florida","country":"US","address":"2720 N Dixie Hwy, Fort Lauderdale, FL 33334, United States","phone":"+1 954-774-3339","website":"https://doghotels.com/dog-fort-lauderdale-2/","pincode":"33334","rating":4.4,"review_count":92,"google_cid":"7210914467204302420","gmb_link":"https://www.google.com/maps?cid=7210914467204302420","active":"yes"}]